[
  {
    "keyword": "Feature",
    "name": "automationteststore testing",
    "line": 2,
    "id": "automationteststore-testing",
    "tags": [
      {
        "name": "@regression",
        "line": 1
      }
    ],
    "uri": "testStore.feature",
    "elements": [
      {
        "id": "automationteststore-testing;",
        "keyword": "Scenario",
        "line": 35,
        "name": "",
        "tags": [
          {
            "name": "@regression",
            "line": 1
          }
        ],
        "type": "scenario",
        "steps": [
          {
            "arguments": [],
            "keyword": "Given ",
            "line": 30,
            "name": "I open automationteststore.com Page",
            "result": {
              "status": "passed",
              "duration": 627000000
            }
          },
          {
            "arguments": [],
            "keyword": "When ",
            "line": 31,
            "name": "I search for Men",
            "result": {
              "status": "passed",
              "duration": 820000000
            }
          },
          {
            "arguments": [],
            "keyword": "Then ",
            "line": 32,
            "name": "I can see PLP with results",
            "result": {
              "status": "passed",
              "duration": 579000000
            }
          }
        ]
      },
      {
        "id": "automationteststore-testing;",
        "keyword": "Scenario",
        "line": 36,
        "name": "",
        "tags": [
          {
            "name": "@regression",
            "line": 1
          }
        ],
        "type": "scenario",
        "steps": [
          {
            "arguments": [],
            "keyword": "Given ",
            "line": 30,
            "name": "I open automationteststore.com Page",
            "result": {
              "status": "passed",
              "duration": 476000000
            }
          },
          {
            "arguments": [],
            "keyword": "When ",
            "line": 31,
            "name": "I search for Skin",
            "result": {
              "status": "passed",
              "duration": 602000000
            }
          },
          {
            "arguments": [],
            "keyword": "Then ",
            "line": 32,
            "name": "I can see PLP with results",
            "result": {
              "status": "passed",
              "duration": 151000000
            }
          }
        ]
      }
    ]
  }
]